sem_emergency_stop-1.3.12.dist-info/licenses/LICENSE
ses/__init__.py
ses/auth.py
ses/banner.py
ses/main.py
sem_emergency_stop-1.3.12.dist-info/METADATA
sem_emergency_stop-1.3.12.dist-info/WHEEL
sem_emergency_stop-1.3.12.dist-info/entry_points.txt
sem_emergency_stop-1.3.12.dist-info/top_level.txt
sem_emergency_stop-1.3.12.dist-info/RECORD
