Metadata-Version: 2.4
Name: sem-emergency-stop
Version: 1.3.12
Summary: Quickly stop all Google Ads advertising
Home-page: https://github.com/getyourguide/sem-emergency-stop
Author: GetYourGuide GmbH
License: Apache License, Version 2.0
Requires-Python: >=3.8
License-File: LICENSE
Requires-Dist: google-ads==26.1.0
Dynamic: author
Dynamic: description
Dynamic: description-content-type
Dynamic: home-page
Dynamic: license
Dynamic: license-file
Dynamic: requires-dist
Dynamic: requires-python
Dynamic: summary
